pyregadj/__init__.py
pyregadj/constants.py
pyregadj/regadjrct.py
pyregadj-0.1.0.dist-info/licenses/LICENSE
pyregadj-0.1.0.dist-info/METADATA
pyregadj-0.1.0.dist-info/WHEEL
pyregadj-0.1.0.dist-info/top_level.txt
pyregadj-0.1.0.dist-info/RECORD
